mcp_wiki_jk/__init__.py
mcp_wiki_jk/__main__.py
mcp_wiki_jk/server.py
mcp_wiki_jk-0.2.0.dist-info/METADATA
mcp_wiki_jk-0.2.0.dist-info/WHEEL
mcp_wiki_jk-0.2.0.dist-info/entry_points.txt
mcp_wiki_jk-0.2.0.dist-info/RECORD
